[[{"todos":[{"id":1,"title":"Faire les courses","completed":false},{"id":2,"title":"Appeler le médecin","completed":true},{"id":3,"title":"Préparer le rapport trimestriel","completed":false},{"id":4,"title":"Nettoyer le garage","completed":false},{"id":5,"title":"Planifier les vacances","completed":true},{"id":6,"title":"Réparer la fuite du robinet","completed":false},{"id":7,"title":"Acheter un cadeau d'anniversaire","completed":false},{"id":8,"title":"Faire du sport","completed":true},{"id":9,"title":"Apprendre une nouvelle langue","completed":false},{"id":10,"title":"Organiser le dîner familial","completed":false},{"id":11,"title":"Changer les pneus de la voiture","completed":true},{"id":12,"title":"Créer un budget mensuel","completed":false},{"id":13,"title":"Rédiger un article de blog","completed":false},{"id":14,"title":"Networking professionnel","completed":false},{"id":15,"title":"Méditer 10 minutes","completed":true},{"id":16,"title":"Répondre aux emails en attente","completed":false},{"id":17,"title":"Faire du bénévolat","completed":false},{"id":18,"title":"Réviser les investissements","completed":false},{"id":19,"title":"Nettoyer le réfrigérateur","completed":true},{"id":20,"title":"Prendre rendez-vous chez le dentiste","completed":false},{"id":21,"title":"Apprendre à cuisiner un nouveau plat","completed":false},{"id":22,"title":"Faire une détox digitale","completed":false},{"id":23,"title":"Organiser les photos de vacances","completed":true},{"id":24,"title":"Réparer la clôture du jardin","completed":false},{"id":25,"title":"Lire un livre","completed":true},{"id":26,"title":"Planter des fleurs","completed":false},{"id":27,"title":"Faire un don à une association","completed":false},{"id":28,"title":"S'inscrire à une formation en ligne","completed":true},{"id":29,"title":"Nettoyer les gouttières","completed":false},{"id":30,"title":"Préparer les taxes","completed":false},{"id":31,"title":"Organiser une soirée jeux","completed":false},{"id":32,"title":"Acheter de nouveaux meubles","completed":false},{"id":33,"title":"Faire réviser la chaudière","completed":true},{"id":34,"title":"Créer un album photo","completed":false},{"id":35,"title":"Apprendre à jouer d'un instrument","completed":false},{"id":36,"title":"Faire du tri dans les vêtements","completed":true},{"id":37,"title":"Visiter un musée","completed":false},{"id":38,"title":"S'occuper de l'entretien de la piscine","completed":false},{"id":39,"title":"Préparer un plan d'épargne","completed":false},{"id":40,"title":"Faire une randonnée","completed":true},{"id":41,"title":"Rénover une pièce de la maison","completed":false},{"id":42,"title":"Créer un site web personnel","completed":false},{"id":43,"title":"Apprendre la photographie","completed":false},{"id":44,"title":"Organiser un pique-nique","completed":true},{"id":45,"title":"Faire du jardinage","completed":false},{"id":46,"title":"Réviser le testament","completed":false},{"id":47,"title":"Prendre des cours de danse","completed":false},{"id":48,"title":"Nettoyer la voiture","completed":true},{"id":49,"title":"Faire du vélo","completed":false},{"id":50,"title":"Organiser les documents importants","completed":false},{"id":51,"title":"Apprendre à coder","completed":true},{"id":52,"title":"Préparer un repas pour un ami","completed":false},{"id":53,"title":"Faire du shopping","completed":false},{"id":54,"title":"Regarder un documentaire","completed":true},{"id":55,"title":"Planifier la retraite","completed":false},{"id":56,"title":"Faire du kayak","completed":false},{"id":57,"title":"Écrire dans un journal","completed":false},{"id":58,"title":"Visiter la famille","completed":true},{"id":59,"title":"Apprendre la méditation","completed":false},{"id":60,"title":"Faire du baby-sitting","completed":false},{"id":61,"title":"Créer un potager","completed":false},{"id":62,"title":"Regarder les étoiles","completed":true},{"id":63,"title":"Faire du bénévolat animalier","completed":false},{"id":64,"title":"Apprendre la menuiserie","completed":false},{"id":65,"title":"Organiser un voyage","completed":true},{"id":66,"title":"Faire du patin à glace","completed":false},{"id":67,"title":"Créer une playlist","completed":false},{"id":68,"title":"Visiter un nouveau restaurant","completed":true},{"id":69,"title":"Apprendre le tricot","completed":false},{"id":70,"title":"Faire du camping","completed":false},{"id":71,"title":"Écrire un poème","completed":false},{"id":72,"title":"Nettoyer le grenier","completed":true},{"id":73,"title":"Apprendre la poterie","completed":false},{"id":74,"title":"Faire du ski","completed":false},{"id":75,"title":"Créer un arbre généalogique","completed":false},{"id":76,"title":"Regarder un coucher de soleil","completed":true},{"id":77,"title":"Apprendre la pêche","completed":false},{"id":78,"title":"Faire du surf","completed":false},{"id":79,"title":"Écrire une lettre à un ami","completed":false},{"id":80,"title":"Nettoyer la terrasse","completed":true},{"id":81,"title":"Apprendre le jardinage hydroponique","completed":false},{"id":82,"title":"Faire du parapente","completed":false},{"id":83,"title":"Créer une œuvre d'art","completed":false},{"id":84,"title":"Visiter un parc national","completed":true},{"id":85,"title":"Apprendre la plongée sous-marine","completed":false},{"id":86,"title":"Faire du yoga","completed":false},{"id":87,"title":"Écrire un livre","completed":false},{"id":88,"title":"Nettoyer les vitres","completed":true},{"id":89,"title":"Apprendre la calligraphie","completed":false},{"id":90,"title":"Faire du tennis","completed":false},{"id":91,"title":"Créer une capsule temporelle","completed":false},{"id":92,"title":"Visiter un marché aux puces","completed":true},{"id":93,"title":"Apprendre l'apiculture","completed":false},{"id":94,"title":"Faire du jogging","completed":false},{"id":95,"title":"Écrire une chanson","completed":false},{"id":96,"title":"Nettoyer le barbecue","completed":true},{"id":97,"title":"Apprendre la mixologie","completed":false},{"id":98,"title":"Faire de l'escalade","completed":false},{"id":99,"title":"Créer un herbier","completed":false},{"id":100,"title":"Visiter un sanctuaire animalier","completed":true}]}]]